random_names/__init__.py
random_names/clean_ten_k.txt
random_names/docker_style.py
random_names/etl/README.md
random_names/etl/__init__.py
random_names/etl/bad_words.txt
random_names/etl/clean_ten_k.txt
random_names/etl/most-common-nouns-english.csv
random_names/etl/people_names.txt
random_names/etl/reform_words.py
random_names/etl/three_k.txt
random_names/etl/word_harvestor.py
random_names/etl/wordlist.10000.txt
random_names/make_name.py
random_names/settings.py
random_names/utils/__init__.py
random_names/utils/files_utils.py
random_names/utils/guards.py
random_names/utils/user_trace.py
random_names-0.2.0.dist-info/LICENSE
random_names-0.2.0.dist-info/METADATA
random_names-0.2.0.dist-info/WHEEL
random_names-0.2.0.dist-info/entry_points.txt
random_names-0.2.0.dist-info/RECORD
