Metadata-Version: 2.1
Name: random-names
Version: 0.2.0
Summary: Convert int to random name, like tree_dance and convert it back to same int.
Home-page: https://github.com/matthewdeanmartin/random_names
License: MIT
Keywords: mneumonic,pseudorandom,name-generator
Author: Matthew Martin
Author-email: matthewdeanmartin@gmail.com
Requires-Python: >=3.6
Classifier: Development Status :: 3 - Alpha
Classifier: Intended Audience :: Developers
Classifier: License :: OSI Approved :: MIT License
Classifier: Operating System :: OS Independent
Classifier: Programming Language :: Python
Classifier: Programming Language :: Python :: 3
Classifier: Programming Language :: Python :: 3.6
Classifier: Programming Language :: Python :: 3.7
Classifier: Programming Language :: Python :: 3.8
Classifier: Programming Language :: Python :: 3.9
Classifier: Programming Language :: Python :: 3.10
Classifier: Programming Language :: Python :: 3.11
Project-URL: Bug Tracker, https://github.com/matthewdeanmartin/random_names/issues
Project-URL: Change Log, https://github.com/matthewdeanmartin/random_names/blob/main/docs/CHANGES.md
Project-URL: Documentation, https://github.com/matthewdeanmartin/random_names
Project-URL: Repository, https://github.com/matthewdeanmartin/random_names
